notion/__init__.py
notion/__version__.py
notion/client.py
notion/endpoints/__init__.py
notion/endpoints/asynchronous.py
notion/endpoints/sync.py
notion/errors.py
notion/helpers.py
notion/types.py
notion_sdk-0.7.0.dist-info/LICENSE
notion_sdk-0.7.0.dist-info/WHEEL
notion_sdk-0.7.0.dist-info/METADATA
notion_sdk-0.7.0.dist-info/RECORD
