Metadata-Version: 2.1
Name: notion-sdk
Version: 0.7.0
Summary: A simple and easy to use Python client for the Notion API
Home-page: https://syncr.so
License: Apache-2.0
Keywords: api,notion,sdk,python
Author: Nicolas Lecoy
Author-email: nicolas@syncr.so
Requires-Python: >=3.7,<4.0
Classifier: License :: OSI Approved :: Apache Software License
Classifier: Programming Language :: Python :: 3
Classifier: Programming Language :: Python :: 3.7
Classifier: Programming Language :: Python :: 3.8
Classifier: Programming Language :: Python :: 3.9
Requires-Dist: httpx (>=0.15.0)
Requires-Dist: pydantic[email] (>=1.7)
Project-URL: Documentation, https://getsyncr.github.io/notion-sdk
Project-URL: Repository, https://github.com/getsyncr/notion-sdk
